griffe-1.12.0.dist-info/METADATA
griffe-1.12.0.dist-info/WHEEL
griffe-1.12.0.dist-info/entry_points.txt
griffe-1.12.0.dist-info/licenses/LICENSE
griffe/__init__.py
griffe/__main__.py
griffe/_internal/__init__.py
griffe/_internal/agents/__init__.py
griffe/_internal/agents/inspector.py
griffe/_internal/agents/nodes/__init__.py
griffe/_internal/agents/nodes/assignments.py
griffe/_internal/agents/nodes/ast.py
griffe/_internal/agents/nodes/docstrings.py
griffe/_internal/agents/nodes/exports.py
griffe/_internal/agents/nodes/imports.py
griffe/_internal/agents/nodes/parameters.py
griffe/_internal/agents/nodes/runtime.py
griffe/_internal/agents/nodes/values.py
griffe/_internal/agents/visitor.py
griffe/_internal/c3linear.py
griffe/_internal/cli.py
griffe/_internal/collections.py
griffe/_internal/debug.py
griffe/_internal/diff.py
griffe/_internal/docstrings/__init__.py
griffe/_internal/docstrings/google.py
griffe/_internal/docstrings/models.py
griffe/_internal/docstrings/numpy.py
griffe/_internal/docstrings/parsers.py
griffe/_internal/docstrings/sphinx.py
griffe/_internal/docstrings/utils.py
griffe/_internal/encoders.py
griffe/_internal/enumerations.py
griffe/_internal/exceptions.py
griffe/_internal/expressions.py
griffe/_internal/extensions/__init__.py
griffe/_internal/extensions/base.py
griffe/_internal/extensions/dataclasses.py
griffe/_internal/finder.py
griffe/_internal/git.py
griffe/_internal/importer.py
griffe/_internal/loader.py
griffe/_internal/logger.py
griffe/_internal/merger.py
griffe/_internal/mixins.py
griffe/_internal/models.py
griffe/_internal/py.typed
griffe/_internal/stats.py
griffe/_internal/tests.py
griffe/py.typed
griffe-1.12.0.dist-info/RECORD
