Metadata-Version: 2.4
Name: griffe
Version: 1.12.0
Summary: Signatures for entire Python programs. Extract the structure, the frame, the skeleton of your project, to generate API documentation or find breaking changes in your API.
Keywords: api,signature,breaking-changes,static-analysis,dynamic-analysis
Author-Email: =?utf-8?q?Timoth=C3=A9e_Mazzucotelli?= <dev@pawamoy.fr>
License-Expression: ISC
License-File: LICENSE
Classifier: Development Status :: 5 - Production/Stable
Classifier: Intended Audience :: Developers
Classifier: Programming Language :: Python
Classifier: Programming Language :: Python :: 3
Classifier: Programming Language :: Python :: 3 :: Only
Classifier: Programming Language :: Python :: 3.9
Classifier: Programming Language :: Python :: 3.10
Classifier: Programming Language :: Python :: 3.11
Classifier: Programming Language :: Python :: 3.12
Classifier: Programming Language :: Python :: 3.13
Classifier: Programming Language :: Python :: 3.14
Classifier: Topic :: Documentation
Classifier: Topic :: Software Development
Classifier: Topic :: Software Development :: Documentation
Classifier: Topic :: Utilities
Classifier: Typing :: Typed
Project-URL: Homepage, https://mkdocstrings.github.io/griffe
Project-URL: Documentation, https://mkdocstrings.github.io/griffe
Project-URL: Changelog, https://mkdocstrings.github.io/griffe/changelog
Project-URL: Repository, https://github.com/mkdocstrings/griffe
Project-URL: Issues, https://github.com/mkdocstrings/griffe/issues
Project-URL: Discussions, https://github.com/mkdocstrings/griffe/discussions
Project-URL: Gitter, https://gitter.im/mkdocstrings/griffe
Project-URL: Funding, https://github.com/sponsors/pawamoy
Requires-Python: >=3.9
Requires-Dist: colorama>=0.4
